ladybug_vectorworks/__init__.py
ladybug_vectorworks/_version.py
ladybug_vectorworks/color.py
ladybug_vectorworks/config.py
ladybug_vectorworks/download.py
ladybug_vectorworks/fromgeometry.py
ladybug_vectorworks/fromobjects.py
ladybug_vectorworks/grasshopper.py
ladybug_vectorworks/intersect.py
ladybug_vectorworks/text.py
ladybug_vectorworks/togeometry.py
ladybug_vectorworks/viewport.py
ladybug_vectorworks/etc/Install_Ladybugtools_mac_v2018.vwx
ladybug_vectorworks/etc/Install_Ladybugtools_mac_v2022.vwx
ladybug_vectorworks/etc/Install_Ladybugtools_windows_vw2018.vwx
ladybug_vectorworks/etc/Install_Ladybugtools_windows_vw2022.vwx
ladybug_vectorworks/etc/JPN_Kagoshima.478270_IWEC.epw
ladybug_vectorworks/etc/Ladybug-sample_v2018.vwx
ladybug_vectorworks/etc/Ladybug-sample_v2022.vwx
ladybug_vectorworks/etc/Node_List_v2018.vwx
ladybug_vectorworks/etc/Node_List_v2022.vwx
ladybug_vectorworks/icon_set/icon_Butterfly Boundary.png
ladybug_vectorworks/icon_set/icon_Butterfly Butterfly.png
ladybug_vectorworks/icon_set/icon_Butterfly Create_Butterfly_Geometry.png
ladybug_vectorworks/icon_set/icon_Butterfly Create_Case_from_Folder.png
ladybug_vectorworks/icon_set/icon_Butterfly Create_Case_from_Geometries.png
ladybug_vectorworks/icon_set/icon_Butterfly Create_Case_from_Tunnel.png
ladybug_vectorworks/icon_set/icon_Butterfly DistanceRefinementMode.png
ladybug_vectorworks/icon_set/icon_Butterfly Function_Object.png
ladybug_vectorworks/icon_set/icon_Butterfly FvSchemes_from_Non-orthogonality.png
ladybug_vectorworks/icon_set/icon_Butterfly Get_Geometry.png
ladybug_vectorworks/icon_set/icon_Butterfly Grading_XYZ.png
ladybug_vectorworks/icon_set/icon_Butterfly Heat_Transfer_Recipe.png
ladybug_vectorworks/icon_set/icon_Butterfly Inlet_Boundary.png
ladybug_vectorworks/icon_set/icon_Butterfly Inlet_Flow-Rate_Boundary.png
ladybug_vectorworks/icon_set/icon_Butterfly LES_Turbulance_Model.png
ladybug_vectorworks/icon_set/icon_Butterfly Laminar_Turbulance_Model.png
ladybug_vectorworks-0.3.1.dist-info/LICENSE
ladybug_vectorworks-0.3.1.dist-info/METADATA
ladybug_vectorworks-0.3.1.dist-info/WHEEL
ladybug_vectorworks-0.3.1.dist-info/top_level.txt
ladybug_vectorworks-0.3.1.dist-info/RECORD
