Metadata-Version: 2.2
Name: ladybug_vectorworks
Version: 0.3.1
Summary: A library for communicating between Ladybug Tools core libraries and Vectorwroks CAD.
Home-page: https://github.com/onokennote/Ladybug-tool_for_Vectorworks.git
Author: onokennote
Author-email: info@onoken-web.com
License: AGPL-3.0
License-File: LICENSE
Requires-Dist: pillow
Requires-Dist: requests
Dynamic: author
Dynamic: author-email
Dynamic: description
Dynamic: description-content-type
Dynamic: home-page
Dynamic: license
Dynamic: requires-dist
Dynamic: summary
